hack4iu/__init__.py
hack4iu/courses.py
hack4iu/utils.py
hack4iu-0.5.0.dist-info/METADATA
hack4iu-0.5.0.dist-info/WHEEL
hack4iu-0.5.0.dist-info/top_level.txt
hack4iu-0.5.0.dist-info/RECORD
